rinoh/__init__.py
rinoh/__main__.py
rinoh/annotation.py
rinoh/attribute.py
rinoh/color.py
rinoh/csl_formatter.py
rinoh/dimension.py
rinoh/document.py
rinoh/draw.py
rinoh/element.py
rinoh/flowable.py
rinoh/highlight.py
rinoh/hyphenator.py
rinoh/image.py
rinoh/index.py
rinoh/inline.py
rinoh/layout.py
rinoh/number.py
rinoh/paper.py
rinoh/paragraph.py
rinoh/reference.py
rinoh/resource.py
rinoh/strings.py
rinoh/structure.py
rinoh/style.py
rinoh/styleds.py
rinoh/styles.py
rinoh/table.py
rinoh/template.py
rinoh/text.py
rinoh/util.py
rinoh/version.py
rinoh/warnings.py
rinoh/backend/__init__.py
rinoh/backend/pdf/__init__.py
rinoh/backend/pdf/cos.py
rinoh/backend/pdf/filter.py
rinoh/backend/pdf/pdfdoccodec.py
rinoh/backend/pdf/reader.py
rinoh/backend/pdf/util.py
rinoh/backend/pdf/xobject/__init__.py
rinoh/backend/pdf/xobject/jpeg.py
rinoh/backend/pdf/xobject/png.py
rinoh/backend/pdf/xobject/purepng.py
rinoh/backend/pdf/xobject/icc/__init__.py
rinoh/backend/pdf/xobject/icc/sRGB_IEC61966-2-1_black_scaled.icc
rinoh/backend/pdf/xobject/icc/sRGB_IEC61966-2-1_black_scaled.txt
rinoh/data/fonts/zapfdingbats.txt
rinoh/data/fonts/adobe14/Courier-Bold.afm
rinoh/data/fonts/adobe14/Courier-BoldOblique.afm
rinoh/data/fonts/adobe14/Courier-Oblique.afm
rinoh/data/fonts/adobe14/Courier.afm
rinoh/data/fonts/adobe14/Helvetica-Bold.afm
rinoh/data/fonts/adobe14/Helvetica-BoldOblique.afm
rinoh/data/fonts/adobe14/Helvetica-Oblique.afm
rinoh/data/fonts/adobe14/Helvetica.afm
rinoh/data/fonts/adobe14/MustRead.html
rinoh/data/fonts/adobe14/Symbol.afm
rinoh/data/fonts/adobe14/Times-Bold.afm
rinoh/data/fonts/adobe14/Times-BoldItalic.afm
rinoh/data/fonts/adobe14/Times-Italic.afm
rinoh/data/fonts/adobe14/Times-Roman.afm
rinoh/data/fonts/adobe14/ZapfDingbats.afm
rinoh/data/hyphen/hyph_en_US.dic
rinoh/data/stylesheets/base14.rts
rinoh/data/stylesheets/sphinx.rts
rinoh/data/stylesheets/sphinx_article.rts
rinoh/data/xml/catalog
rinoh/data/xml/docutils/docutils.dtd
rinoh/data/xml/docutils/soextblx.dtd
rinohtype_reloaded-0.3.3.dist-info/LICENSE
rinohtype_reloaded-0.3.3.dist-info/METADATA
rinohtype_reloaded-0.3.3.dist-info/WHEEL
rinohtype_reloaded-0.3.3.dist-info/entry_points.txt
rinohtype_reloaded-0.3.3.dist-info/top_level.txt
rinohtype_reloaded-0.3.3.dist-info/RECORD
