Metadata-Version: 2.1
Name: rinohtype-reloaded
Version: 0.3.3
Summary: The Python document processor
Home-page: https://github.com/brechtm/rinohtype
Author: Brecht Machiels
Author-email: brecht@mos6581.org
License: UNKNOWN
Keywords: rst xml pdf opentype
Platform: UNKNOWN
Classifier: Environment :: Console
Classifier: Environment :: Other Environment
Classifier: Environment :: Web Environment
Classifier: Development Status :: 4 - Beta
Classifier: Intended Audience :: Developers
Classifier: Intended Audience :: End Users/Desktop
Classifier: License :: OSI Approved :: GNU Affero General Public License v3
Classifier: Operating System :: OS Independent
Classifier: Programming Language :: Python :: 3 :: Only
Classifier: Programming Language :: Python :: 3.4
Classifier: Programming Language :: Python :: 3.5
Classifier: Programming Language :: Python :: 3.6
Classifier: Topic :: Printing
Classifier: Topic :: Software Development :: Libraries :: Python Modules
Classifier: Topic :: Text Processing :: Fonts
Classifier: Topic :: Text Processing :: Markup
Classifier: Topic :: Text Processing :: Markup :: XML
Requires-Python: >= 3.4
Requires-Dist: setuptools
Requires-Dist: pip
Requires-Dist: docutils
Requires-Dist: recommonmark
Requires-Dist: rinoh-typeface-texgyrecursor (>=0.1.1)
Requires-Dist: rinoh-typeface-texgyreheros (>=0.1.1)
Requires-Dist: rinoh-typeface-texgyrepagella (>=0.1.1)
Requires-Dist: rinoh-typeface-dejavuserif
Provides-Extra: bitmap
Requires-Dist: Pillow ; extra == 'bitmap'
